wpilib/geometry/__init__.py
wpilib/geometry/rotation2d.py
wpilib/geometry/translation2d.py
wpilib/geometry/twist2d.py
wpilib/kinematics/__init__.py
wpilib/kinematics/chassisspeeds.py
wpilib/kinematics/swerve.py
wpilib.kinematics-0.1.1.dist-info/LICENSE.txt
wpilib.kinematics-0.1.1.dist-info/METADATA
wpilib.kinematics-0.1.1.dist-info/WHEEL
wpilib.kinematics-0.1.1.dist-info/top_level.txt
wpilib.kinematics-0.1.1.dist-info/RECORD
